django_mysql_fields/__init__.py
django_mysql_fields/settings.py
django_mysql_fields/urls.py
django_mysql_fields/wsgi.py
django_mysql_fields/fields/__init__.py
django_mysql_fields/fields/jsonfield.py
django_mysql_fields/fields/uuidfield.py
django_mysql_fields/forms/__init__.py
django_mysql_fields/forms/jsonfield.py
django_mysql_fields/widgets/__init__.py
django_mysql_fields/widgets/jsonfield.py
django_mysql_fields-0.1.2.dist-info/DESCRIPTION.rst
django_mysql_fields-0.1.2.dist-info/METADATA
django_mysql_fields-0.1.2.dist-info/RECORD
django_mysql_fields-0.1.2.dist-info/WHEEL
django_mysql_fields-0.1.2.dist-info/metadata.json
django_mysql_fields-0.1.2.dist-info/top_level.txt
