Metadata-Version: 1.1
Name: django-mysql-fields
Version: 0.1.2
Summary: Useful Django fields for use with MySQL.
Home-page: https://github.com/multiplay/django-mysql-fields
Author: Multiplay UK Ltd
Author-email: support@multiplay.co.uk
License: BSD License
Platform: UNKNOWN
Classifier: Environment :: Web Environment
Classifier: Framework :: Django
Classifier: Framework :: Django :: 1.9
Classifier: Intended Audience :: Developers
Classifier: Operating System :: OS Independent
Classifier: Programming Language :: Python
Classifier: Programming Language :: Python :: 3
Classifier: Programming Language :: Python :: 3.4
Classifier: Programming Language :: Python :: 3.5
Classifier: Topic :: Internet :: WWW/HTTP
Classifier: Topic :: Internet :: WWW/HTTP :: Dynamic Content
